Workbook

Sheet Assumptions
A1: Assumptions | B1: Value | C1: Source/Notes
A2: Baseline annual income (no secondary, KES) | B2: 70000 | C2: Estimate - informal sector, refine w/ KNBS data
A3: Wage premium per year (base case) | B3: 0.1 | C3: Psacharopoulos/World Bank global avg ~10%
A4: Wage premium per year (low case) | B4: 0.05 | C4: Conservative estimate
A5: Wage premium per year (girls-specific, high) | B5: 0.12 | C5: Bono/Citi development finance estimate
A6: Years of secondary school | B6: 4 | C6: Standard Kenyan secondary cycle
A7: Working years | B7: 35 | C7: Standard assumption
A8: Discount rate | B8: 0.08 | C8: Standard DCF assumption
A9: Cost per year of secondary school (KES) | B9: 20000 | C9: Estimate - public day school, refine w/ MOE data

Sheet Model 
A1: Model
A2: Annual income with secondary (KES) | B2: =Assumptions!B2*(1+Assumptions!B3)^Assumptions!B6 -> 102487
A3: Additional annual income (KES) | B3: =B2-Assumptions!B2 -> 32487
A4: Total cost of schooling (KES) | B4: =Assumptions!B9*Assumptions!B6 -> 80000
A5: Lifetime additional income, undiscounted (KES) | B5: =B3*Assumptions!B7 -> 1137045
A6: Simple ROI (%) | B6: =(B5-B4)/B4*100 -> 1321.3063
A7: NPV of additional income stream (KES) | B7: =NPV(Assumptions!B8,B10:B44) -> 378621.96
A8: Discounted ROI (%) | B8: =(B7-B4)/B4*100 -> 373.27745
B10: =$B$3 -> 32487
B11: =$B$3 -> 32487
B12: =$B$3 -> 32487
B13: =$B$3 -> 32487
B14: =$B$3 -> 32487
B15: =$B$3 -> 32487
B16: =$B$3 -> 32487
B17: =$B$3 -> 32487
B18: =$B$3 -> 32487
B19: =$B$3 -> 32487
B20: =$B$3 -> 32487
B21: =$B$3 -> 32487
... B44: =$B$3 -> 32487

Sheet Scenarios
A1: Scenario | B1: Wage Premium | C1: Additional Income/yr (KES) | D1: NPV (KES) | E1: Discounted ROI (%)D
A2: Low | B2: =Assumptions!B4 -> 0.05 | C2: =Assumptions!B2*(1+B2)^Assumptions!B6-Assumptions!B2 -> 15085.438 | D2: =C2*((1-(1+Assumptions!B8)^-Assumptions!B7)/Assumptions!B8) -> 175814.26 | E2: =(D2-Assumptions!B9*Assumptions!B6)/(Assumptions!B9*Assumptions!B6)*100 -> 119.76783
A3: Base | B3: =Assumptions!B3 -> 0.1 | C3: =Assumptions!B2*(1+B3)^Assumptions!B6-Assumptions!B2 -> 32487 | D3: =C3*((1-(1+Assumptions!B8)^-Assumptions!B7)/Assumptions!B8) -> 378621.96 | E3: =(D3-Assumptions!B9*Assumptions!B6)/(Assumptions!B9*Assumptions!B6)*100 -> 373.27745
A4: High | B4: =Assumptions!B5 -> 0.12 | C4: =Assumptions!B2*(1+B4)^Assumptions!B6-Assumptions!B2 -> 40146.355 | D4: =C4*((1-(1+Assumptions!B8)^-Assumptions!B7)/Assumptions!B8) -> 467888.44 | E4: =(D4-Assumptions!B9*Assumptions!B6)/(Assumptions!B9*Assumptions!B6)*100 -> 484.86054

Sheet Summary
A1: Girls' Education ROI Model - Kenya
A2: Rachael Richard | Columbia University
A4: KEY FINDING
A5: Four years of girls' secondary education in rural Kenya generates a 373% discounted return on investment in the base case rising to 485% under girls-specific wage premium assumptions.
A7: SCENARIO RESULTS
A8: Scenario | B8: Wage Premium | C8: Discounted ROI (%)
A9: Low | B9: 0.05 | C9: 1.2
A10: Base | B10: 0.1 | C10: 3.73
A11: High | B11: 0.12 | C11: 4.85
A13: METHODOLOGY NOTES
A14: Baseline income: KES 70,000/yr (rural informal sector estimate)
A15: Total schooling cost: KES 80,000 (KES 20,000/yr × 4 years)
A16: Discount rate: 8% over 35-year working life
A17: Wage premium source: Psacharopoulos & Patrinos (2018), Education Economics 26(5)
A18: Kenya evidence: Ozier (2015), World Bank Policy Research WP 7384
